py_comment_times/__init__.py
py_comment_times/get_times_far.py
py_comment_times/get_times_format.py
py_comment_times-0.0.1.dist-info/METADATA
py_comment_times-0.0.1.dist-info/WHEEL
py_comment_times-0.0.1.dist-info/top_level.txt
py_comment_times-0.0.1.dist-info/RECORD
