Metadata-Version: 2.1
Name: py-comment-times
Version: 0.0.1
Summary: Python get time package
Home-page: UNKNOWN
Author: Riyad Zaigirdar
Author-email: <riyadzaigir280@gmail.com>
License: UNKNOWN
Keywords: python,times,datetime,comment,post,ago,far,format
Platform: UNKNOWN
Classifier: Development Status :: 1 - Planning
Classifier: Intended Audience :: Developers
Classifier: Programming Language :: Python :: 3
Classifier: Operating System :: Unix
Classifier: Operating System :: MacOS :: MacOS X
Classifier: Operating System :: Microsoft :: Windows
